mr_cli/__init__.py
mr_cli/__main__.py
mr_cli-0.0.3.dist-info/entry_points.txt
mr_cli-0.0.3.dist-info/LICENSE
mr_cli-0.0.3.dist-info/WHEEL
mr_cli-0.0.3.dist-info/METADATA
mr_cli-0.0.3.dist-info/RECORD
