Metadata-Version: 2.1
Name: mr-cli
Version: 0.0.3
Summary: 
License: MIT
Author: GreyElaina
Author-email: GreyElaina@outlook.com
Requires-Python: >=3.8,<4.0
Classifier: License :: OSI Approved :: MIT License
Classifier: Programming Language :: Python :: 3
Classifier: Programming Language :: Python :: 3.8
Classifier: Programming Language :: Python :: 3.9
Requires-Dist: rich (>=10.8.0,<11.0.0)
Requires-Dist: typer (>=0.3.2,<0.4.0)
